{
  "gitSyncId": "69df81de1424f43dde27e012_efb2e6b6-6ae3-4c93-814e-372fb6d1beef",
  "id": "020 - Tutores_JSvalidateButtonPART.resetFormPART",
  "pluginId": "js-plugin",
  "pluginType": "JS",
  "unpublishedAction": {
    "actionConfiguration": {
      "encodeParamsToggle": true,
      "jsArguments": [],
      "paginationType": "NONE",
      "timeoutInMillisecond": 10000
    },
    "collectionId": "020 - Tutores_JSvalidateButtonPART",
    "confirmBeforeExecute": false,
    "datasource": {
      "isAutoGenerated": false,
      "name": "UNUSED_DATASOURCE",
      "pluginId": "js-plugin"
    },
    "dynamicBindingPathList": [
      {
        "key": "body"
      }
    ],
    "fullyQualifiedName": "JSvalidateButtonPART.resetFormPART",
    "name": "resetFormPART",
    "pageId": "020 - Tutores",
    "runBehaviour": "MANUAL",
    "userSetOnLoad": false
  }
}