{
  "accentColor": "{{appsmith.theme.colors.primaryColor}}",
  "animateLoading": true,
  "borderRadius": "{{appsmith.theme.borderRadius.appBorderRadius}}",
  "bottomRow": 25,
  "boxShadow": "none",
  "defaultOptionValue": "{{ ((options, serverSideFiltering) => (  \n  appsmith.store.modalContexto?.acaoTipo === \"ADICIONAR\" \n  ? \"false\" \n  : String(TableProdutos.selectedRow.serv001_controla_estoque ?? \"false\")\n))(Select1Controla.options, Select1Controla.serverSideFiltering) }}",
  "dynamicBindingPathList": [
    {
      "key": "accentColor"
    },
    {
      "key": "borderRadius"
    },
    {
      "key": "defaultOptionValue"
    }
  ],
  "dynamicHeight": "FIXED",
  "dynamicPropertyPathList": [
    {
      "key": "sourceData"
    }
  ],
  "dynamicTriggerPathList": [],
  "isDisabled": false,
  "isFilterable": true,
  "isLoading": false,
  "isRequired": true,
  "isVisible": true,
  "key": "3x8hw6xtqw",
  "labelAlignment": "left",
  "labelPosition": "Top",
  "labelText": "Ctrl Estoque?",
  "labelTextSize": "0.875rem",
  "labelWidth": 5,
  "leftColumn": 0,
  "maxDynamicHeight": 9000,
  "minDynamicHeight": 4,
  "minWidth": 450,
  "mobileBottomRow": 18,
  "mobileLeftColumn": 0,
  "mobileRightColumn": 20,
  "mobileTopRow": 11,
  "needsErrorInfo": false,
  "optionLabel": "name",
  "optionValue": "code",
  "parentColumnSpace": 7.1826171875,
  "parentId": "bta2kewsl8",
  "parentRowSpace": 10,
  "placeholderText": "Select option",
  "renderMode": "CANVAS",
  "responsiveBehavior": "fill",
  "rightColumn": 20,
  "serverSideFiltering": false,
  "sourceData": "[\n  { \"name\": \"SIM\", \"code\": \"true\" },\n  { \"name\": \"NÃO\", \"code\": \"false\" }\n]",
  "topRow": 18,
  "type": "SELECT_WIDGET",
  "version": 1,
  "widgetId": "k650bo7fg3",
  "widgetName": "Select1Controla"
}