{
  "gitSyncId": "69b814afccdcda4eb595c07f_6f412304-a94d-4559-bd42-f1097a8fb337",
  "id": "011 - Imunizante_SelectVia",
  "pluginId": "postgres-plugin",
  "pluginType": "DB",
  "unpublishedAction": {
    "actionConfiguration": {
      "body": "SELECT *\nFROM \"{{JSutils.currentSchema()}}\".hotimun005\nWHERE imun005_deleted <> true\nORDER BY imun005_desc, imun005_id;",
      "encodeParamsToggle": true,
      "paginationType": "NONE",
      "pluginSpecifiedTemplates": [
        {
          "value": false
        }
      ],
      "timeoutInMillisecond": 10000
    },
    "confirmBeforeExecute": false,
    "datasource": {
      "id": "dbhotelpet",
      "isAutoGenerated": false,
      "name": "dbhotelpet",
      "pluginId": "postgres-plugin"
    },
    "dynamicBindingPathList": [
      {
        "key": "body"
      }
    ],
    "name": "SelectVia",
    "pageId": "011 - Imunizante",
    "runBehaviour": "AUTOMATIC",
    "userSetOnLoad": false
  }
}