{
  "gitSyncId": "69b814afccdcda4eb595c07f_730b764c-c3bc-4906-beda-96a92bde36ad",
  "id": "017 - Acomodações_JSvalidateButton.podeCancelar",
  "pluginId": "js-plugin",
  "pluginType": "JS",
  "unpublishedAction": {
    "actionConfiguration": {
      "encodeParamsToggle": true,
      "jsArguments": [],
      "paginationType": "NONE",
      "timeoutInMillisecond": 10000
    },
    "collectionId": "017 - Acomodações_JSvalidateButton",
    "confirmBeforeExecute": false,
    "datasource": {
      "isAutoGenerated": false,
      "name": "UNUSED_DATASOURCE",
      "pluginId": "js-plugin"
    },
    "dynamicBindingPathList": [
      {
        "key": "body"
      }
    ],
    "fullyQualifiedName": "JSvalidateButton.podeCancelar",
    "name": "podeCancelar",
    "pageId": "017 - Acomodações",
    "runBehaviour": "MANUAL",
    "userSetOnLoad": false
  }
}