{
  "gitSyncId": "69b814afccdcda4eb595c07f_943f47bc-57a4-46bc-83f5-9789265ab44f",
  "id": "011 - Imunizante_JSvalidateButton.temAlteracao",
  "pluginId": "js-plugin",
  "pluginType": "JS",
  "unpublishedAction": {
    "actionConfiguration": {
      "encodeParamsToggle": true,
      "jsArguments": [],
      "paginationType": "NONE",
      "timeoutInMillisecond": 10000
    },
    "collectionId": "011 - Imunizante_JSvalidateButton",
    "confirmBeforeExecute": false,
    "datasource": {
      "isAutoGenerated": false,
      "name": "UNUSED_DATASOURCE",
      "pluginId": "js-plugin"
    },
    "dynamicBindingPathList": [
      {
        "key": "body"
      }
    ],
    "fullyQualifiedName": "JSvalidateButton.temAlteracao",
    "name": "temAlteracao",
    "pageId": "011 - Imunizante",
    "runBehaviour": "MANUAL",
    "userSetOnLoad": false
  }
}