{
  "animateLoading": true,
  "borderRadius": "{{appsmith.theme.borderRadius.appBorderRadius}}",
  "bottomRow": 6,
  "boxShadow": "none",
  "buttonColor": "{{appsmith.theme.colors.primaryColor}}",
  "buttonVariant": "PRIMARY",
  "disabledWhenInvalid": false,
  "dynamicBindingPathList": [
    {
      "key": "buttonColor"
    },
    {
      "key": "borderRadius"
    }
  ],
  "dynamicPropertyPathList": [
    {
      "key": "onClick"
    }
  ],
  "dynamicTriggerPathList": [
    {
      "key": "onClick"
    }
  ],
  "iconAlign": "left",
  "iconName": "add",
  "isDefaultClickDisabled": true,
  "isDisabled": false,
  "isLoading": false,
  "isVisible": true,
  "key": "mfa917wnro",
  "leftColumn": 48,
  "minWidth": 120,
  "mobileBottomRow": 4,
  "mobileLeftColumn": 44,
  "mobileRightColumn": 60,
  "mobileTopRow": 0,
  "needsErrorInfo": false,
  "onClick": "{{\n  (async () => {\n    // 1. Define o contexto para ADICIONAR\n    await storeValue('modalContexto', {\n      acaoTipo: \"ADICIONAR\",\n      acaoBotao: \"SALVAR\",\n    });\n    // 2. Limpa o campo para garantir que está vazio\n   resetWidget(\"InputDescricao\", true);\n    // 3. Reinicia o contador de inatividade (Sinaliza que o usuário está ativo)\n JSutils.resetInactivityTimer();\n  })()\n}}",
  "parentColumnSpace": 4.21875,
  "parentId": "o4a284dmrc",
  "parentRowSpace": 10,
  "placement": "CENTER",
  "recaptchaType": "V3",
  "renderMode": "CANVAS",
  "resetFormOnClick": false,
  "responsiveBehavior": "hug",
  "rightColumn": 60,
  "text": "NOVO",
  "tooltip": "adicionar um novo registro",
  "topRow": 1,
  "type": "BUTTON_WIDGET",
  "version": 1,
  "widgetId": "u9l5276nhn",
  "widgetName": "ButtonNew"
}