{
  "gitSyncId": "69b814afccdcda4eb595c07f_53f87a68-e4b3-44d9-90d0-bc9c492d8971",
  "id": "013 - Porte_JSutils.currentSchema",
  "pluginId": "js-plugin",
  "pluginType": "JS",
  "unpublishedAction": {
    "actionConfiguration": {
      "encodeParamsToggle": true,
      "jsArguments": [],
      "paginationType": "NONE",
      "timeoutInMillisecond": 10000
    },
    "collectionId": "013 - Porte_JSutils",
    "confirmBeforeExecute": false,
    "datasource": {
      "isAutoGenerated": false,
      "name": "UNUSED_DATASOURCE",
      "pluginId": "js-plugin"
    },
    "dynamicBindingPathList": [
      {
        "key": "body"
      }
    ],
    "fullyQualifiedName": "JSutils.currentSchema",
    "name": "currentSchema",
    "pageId": "013 - Porte",
    "runBehaviour": "MANUAL",
    "userSetOnLoad": false
  }
}