{
  "gitSyncId": "69df81de1424f43dde27e012_787c5910-b8f8-49a0-aef9-43e3f90eafb7",
  "id": "021 - Particularidades_JSutils.aoCarregarPagina",
  "pluginId": "js-plugin",
  "pluginType": "JS",
  "unpublishedAction": {
    "actionConfiguration": {
      "encodeParamsToggle": true,
      "jsArguments": [],
      "paginationType": "NONE",
      "timeoutInMillisecond": 10000
    },
    "collectionId": "021 - Particularidades_JSutils",
    "confirmBeforeExecute": false,
    "datasource": {
      "isAutoGenerated": false,
      "name": "UNUSED_DATASOURCE",
      "pluginId": "js-plugin"
    },
    "dynamicBindingPathList": [
      {
        "key": "body"
      }
    ],
    "fullyQualifiedName": "JSutils.aoCarregarPagina",
    "name": "aoCarregarPagina",
    "pageId": "021 - Particularidades",
    "runBehaviour": "ON_PAGE_LOAD",
    "userSetOnLoad": true
  }
}